Metadata-Version: 2.1
Name: l4casadi
Version: 2.0.0
Summary: Integrate PyTorch Model in CasADi graphs.
Author-email: Tim Salzmann <Tim.Salzmann@tum.de>
Project-URL: Homepage, https://github.com/Tim-Salzmann/l4casadi
Classifier: Programming Language :: Python :: 3
Classifier: Programming Language :: C++
Classifier: License :: OSI Approved :: MIT License
Classifier: Operating System :: OS Independent
Requires-Python: >=3.8
License-File: LICENSE
Requires-Dist: torch
Requires-Dist: casadi>=3.6
Requires-Dist: jinja2>=3.1
